postmanscript2requests/__init__.py
postmanscript2requests/p2r.py
postmanscript2requests-0.1.dist-info/LICENSE
postmanscript2requests-0.1.dist-info/METADATA
postmanscript2requests-0.1.dist-info/WHEEL
postmanscript2requests-0.1.dist-info/top_level.txt
postmanscript2requests-0.1.dist-info/RECORD
