Metadata-Version: 2.1
Name: postmanscript2requests
Version: 0.1
Summary: PostmanScript to RequestsScript
Home-page: https://github.com/tser/p2r
Author: Tser
Author-email: 807447312@qq.com
License: UNKNOWN
Platform: UNKNOWN
Classifier: Programming Language :: Python :: 3
Classifier: License :: OSI Approved :: MIT License
Classifier: Operating System :: OS Independent
Requires-Python: >=3.4
